odoo/addons/mrp_operating_unit_access_all/README.rst
odoo/addons/mrp_operating_unit_access_all/__init__.py
odoo/addons/mrp_operating_unit_access_all/__manifest__.py
odoo/addons/mrp_operating_unit_access_all/i18n/mrp_operating_unit_access_all.pot
odoo/addons/mrp_operating_unit_access_all/readme/CONFIGURE.rst
odoo/addons/mrp_operating_unit_access_all/readme/CONTRIBUTORS.rst
odoo/addons/mrp_operating_unit_access_all/readme/DESCRIPTION.rst
odoo/addons/mrp_operating_unit_access_all/security/mrp_security.xml
odoo/addons/mrp_operating_unit_access_all/static/description/icon.png
odoo/addons/mrp_operating_unit_access_all/static/description/index.html
odoo_addon_mrp_operating_unit_access_all-15.0.1.0.0.2.dist-info/METADATA
odoo_addon_mrp_operating_unit_access_all-15.0.1.0.0.2.dist-info/WHEEL
odoo_addon_mrp_operating_unit_access_all-15.0.1.0.0.2.dist-info/top_level.txt
odoo_addon_mrp_operating_unit_access_all-15.0.1.0.0.2.dist-info/RECORD
